{
    "header" : "Technologies",
    "items": [
        { "id": "html", "name": "html" , "icon":  "<i class='fa-brands fa-html5'></i>"},
        { "id": "css", "name": "css" , "icon":  "<i class='fa-brands fa-css3-alt'></i>"},
        { "id": "sass", "name": "sass" , "icon":  "<i class='fa-brands fa-sass'></i>"},
        { "id": "bootstrap", "name": "bootstrap" , "icon":  "<i class='fa-brands fa-bootstrap'></i>"},
        { "id": "js", "name": "javascript", "icon":  "<i class='devicon-javascript-plain'></i>"},
        { "id": "ts", "name": "typescript", "icon":  "<i class='devicon-typescript-plain'></i>"},
        { "id": "jq", "name": "jquery", "icon":  "<i class='devicon-jquery-plain'></i>"},
        { "id": "php", "name": "php" , "icon":  "<i class='fa-brands fa-php'></i>"},
        { "id": "laravel", "name": "laravel" , "icon":  "<i class='fa-brands fa-laravel'></i>"},
        { "id": "angular", "name": "angular" , "icon":  "<i class='fa-brands fa-angular'></i>"},
        { "id": "git", "name": "git" , "icon":  "<i class='fa-brands fa-git-alt'></i>"},
        { "id": "mysql", "name": "mysql" , "icon":  "<i class='devicon-mysql-plain'></i>"},
        { "id": "postgres", "name": "postgres" , "icon":  "<i class='devicon-postgresql-plain'></i>"},
        { "id": "mssql", "name": "mssql" , "icon":  "<i class='devicon-microsoftsqlserver-plain'></i>"},
        { "id": "azure", "name": "azure" , "icon":  "<i class='devicon-azure-plain'></i>"},
        { "id": "bash", "name": "bash" , "icon":  "<i class='devicon-bash-plain'></i>"},
        { "id": "ubuntu", "name": "ubuntu" , "icon":  "<i class='devicon-ubuntu-plain'></i>"},
        { "id": "docker", "name": "docker" , "icon":  "<i class='devicon-docker-plain'></i>"},
        { "id": "redis", "name": "redis" , "icon":  "<i class='devicon-redis-plain'></i>"},
        { "id": "trello", "name": "trello" , "icon":  "<i class='fa-brands fa-trello'></i>"},
        { "id": "adobe-xd", "name": "adobe xd" , "icon":  "<i class='devicon-xd-plain'></i>"}
    ]
}
